facts/__init__.py
facts/__main__.py
facts/conf.py
facts/formatters.py
facts/logical.py
facts/serializer.py
facts/targeting.py
facts/user_data.py
facts/contribs/__init__.py
facts/grafts/__init__.py
facts/grafts/system_grafts.py
facts/grafts/user_grafts.py
facts-0.4.dist-info/DESCRIPTION.rst
facts-0.4.dist-info/entry_points.txt
facts-0.4.dist-info/METADATA
facts-0.4.dist-info/metadata.json
facts-0.4.dist-info/RECORD
facts-0.4.dist-info/top_level.txt
facts-0.4.dist-info/WHEEL
