Metadata-Version: 1.1
Name: facts
Version: 0.4
Summary: Return facts of server
Home-page: https://github.com/johnnoone/facts
Author: Xavier Barbosa
Author-email: clint.northwood@gmail.com
License: UNKNOWN
Keywords: infrastructure,asyncio
Platform: UNKNOWN
Classifier: Development Status :: 3 - Alpha
Classifier: Intended Audience :: Developers
Classifier: License :: OSI Approved :: BSD License
Classifier: Operating System :: OS Independent
Classifier: Programming Language :: Python :: 3.3
Classifier: Programming Language :: Python :: 3.4
Classifier: Topic :: System :: Clustering
